mchains/AMarkovChains.py
mchains/MarkovChains.py
mchains/__init__.py
mchains-0.3.dist-info/METADATA
mchains-0.3.dist-info/WHEEL
mchains-0.3.dist-info/top_level.txt
mchains-0.3.dist-info/RECORD
