Metadata-Version: 2.1
Name: mchains
Version: 0.3
Summary: markov chains tools
Home-page: https://github.com/Ethosa/mchains
Author: Ethosa
Author-email: social.ethosa@gmail.com
License: LGPLv3
Project-URL: Github, https://github.com/Ethosa/mchains
Keywords: markov chains
Platform: UNKNOWN
Classifier: Development Status :: 3 - Alpha
Classifier: Programming Language :: Python :: 3
Classifier: Programming Language :: Python :: 3.4
Classifier: Programming Language :: Python :: 3.5
Classifier: Programming Language :: Python :: 3.6
Classifier: Programming Language :: Python :: 3.7
Classifier: License :: OSI Approved :: GNU Lesser General Public License v3 (LGPLv3)
Classifier: Operating System :: OS Independent
Requires-Python: >=3
Requires-Dist: regex
